vfxtool/__init__.py
vfxtool/dataIO.py
vfxtool/lineup.py
vfxtool/main.py
vfxtool/shotsInfo.py
vfxtool-0.0.4.dist-info/LICENSE.txt
vfxtool-0.0.4.dist-info/METADATA
vfxtool-0.0.4.dist-info/WHEEL
vfxtool-0.0.4.dist-info/top_level.txt
vfxtool-0.0.4.dist-info/RECORD
